SPI/spi.v
//
//
`define    SIZE     8
module spi (
    input clk,    // Clock
    input rst_n,  // Asynchronous reset active low
    input rd,
    input wr,
    input si,
    input [`SIZE - 1:0] data_in,
    output sclk,
    output so,
    output cs,
    output [`SIZE -1:0] data_out
);

parameter   bit7=4'd0,
            bit6 = 4'd1,
            bit5 = 4'd2,
            bit4 = 4'd3,
            bit3 = 4'd4,
            bit2 = 4'd5,
            bit1 = 4'd6,
            bit0 = 4'd7,
            bit_end = 4'd8;
parameter   bit70 = 4'd0,
            bit60 = 4'd1,
            bit50 = 4'd2,
            bit40 = 4'd3,
            bit30 = 4'd4,
            bit20 = 4'd5,
            bit10 = 4'd6,
            bit00 = 4'd7,
            bit0_end = 4'd8;

wire [`SIZE-1:0] data_out;
reg [`SIZE-1:0] dout_buf;
reg FF;
reg sclk;
reg so;
reg cs;

reg [3:0] send_state;
reg [3:0] receive_state;

always @(posedge clk or negedge rst_n) begin 
    if(~rst_n) begin
        sclk <= 0;
        cs <= 1;
    end 
    else if(rd|wr) begin
        /* code */
        sclk <= ~sclk;
        cs <= 0;
    end
    else begin
        sclk <= 0;
        cs <= 1;
    end
    
end

assign data_out = (FF==1)? dout_buf:8'hz;


always @(posedge clk ) begin 
    if(wr) begin
        send_state <= 4'b0;
        send_data();
    end 
end

always @(posedge clk ) begin 
    if(rd) begin
         receive_state <= bit70;
         FF <= 0;
         receive_data();
    end 
end

task send_data;
    begin
        case (send_state)
            bit7: begin
                    so <= data_in[7];
                    send_state<=bit6;
                 end
            bit6:begin
                so <= data_in[6];
                send_state <= bit5;
            end
            bit5:begin
                so <= data_in[5];
                send_state <= bit4;
            end
            bit4:begin
                so <= data_in[4];
                send_state <= bit3;
            end
            bit3:begin
                so <= data_in[3];
                send_state <= bit2;
            end
            bit2:begin
                so <= data_in[2];
                send_state <= bit1;
            end
            bit1:begin
                so <= data_in[1];
                send_state <= bit0;
            end
            bit0:begin
                so <= data_in[0];
                send_state <= bit_end;
            end
            bit_end : begin
                so <= 1'bz;
                send_state <= bit7;
            end
            default: ;
        endcase
    end
endtask 

task receive_data;
    begin
        case (receive_state)
            bit70:begin
                dout_buf[7] <= si;
                receive_state <= bit60;
            end
            bit60:begin
                dout_buf[6] <= si;
                receive_state <= bit50;
            end
            bit50:begin
                dout_buf[5] <= si;
                receive_state <= bit40;
            end
            bit40:begin
                dout_buf[4] <= si;
                receive_state <= bit30;
            end
            bit30:begin
                dout_buf[3] <= si;
                receive_state <= bit20;
            end
            bit20:begin
                dout_buf[2] <= si;
                receive_state <= bit10;
            end
            bit10:begin
                dout_buf[1] <= si;
                receive_state <= bit00;
            end
            bit00:begin
                dout_buf[0] <= si;
                receive_state <= bit0_end;
            end
            bit0_end:begin
                dout_buf <= 8'hzz;
                receive_state <= bit70;
            end
            default : /* default */;
        endcase
    end
endtask 


endmodule

SPI/test_top.v
`timescale   1ns / 1ps

`define  HALF_PERIOD 10
`define  SIM_TIME    600
`define  SIZE        8

module test_top ;
    reg clk;    // Clock
    reg rst_n;  // Asynchronous reset active low
    reg rd;
    reg wr;
    reg si;
    reg [`SIZE - 1:0] data_in;

    wire sclk;
    wire so;
    wire cs;
    wire [`SIZE -1:0] data_out;

    reg [`SIZE-1:0] si_buf;

    //generate clk
    initial
    begin
        clk = 0;
        forever #(`HALF_PERIOD) clk = ~clk;
    end

    initial
    begin
        $display("spi test_top start");
        $dumpfile("test_top.vcd");
        $dumpvars(0,test_top);

        data_in = 8'b0101_0011;
        si_buf = 8'b1001_1010;
        //sclk = clk;
        rst_n = 0;
        #(`HALF_PERIOD);
        rst_n = 1;
        wr = 1;
        rd = 1;
        #400 rd = 0;

        #(`SIM_TIME) $finish;
    end

    always @(posedge clk ) begin 
        si_buf = si_buf << 1;
        si <= si_buf[7];
    end

    spi spi_test (clk,rst_n,rd,wr,si,data_in,sclk,so,cs,data_out);

endmodule

SPI/test_top.vcd
$date
	Tue Mar 19 16:44:11 2019
$end
$version
	Icarus Verilog
$end
$timescale
	1ps
$end
$scope module test_top $end
$var wire 1 ! so $end
$var wire 1 " sclk $end
$var wire 8 # data_out [7:0] $end
$var wire 1 $ cs $end
$var reg 1 % clk $end
$var reg 8 & data_in [7:0] $end
$var reg 1 ' rd $end
$var reg 1 ( rst_n $end
$var reg 1 ) si $end
$var reg 8 * si_buf [7:0] $end
$var reg 1 + wr $end
$scope module spi_test $end
$var wire 1 % clk $end
$var wire 8 , data_in [7:0] $end
$var wire 1 ' rd $end
$var wire 1 ( rst_n $end
$var wire 1 ) si $end
$var wire 1 + wr $end
$var wire 8 - data_out [7:0] $end
$var reg 1 . FF $end
$var reg 1 $ cs $end
$var reg 8 / dout_buf [7:0] $end
$var reg 4 0 receive_state [3:0] $end
$var reg 1 " sclk $end
$var reg 4 1 send_state [3:0] $end
$var reg 1 ! so $end
$scope task receive_data $end
$upscope $end
$scope task send_data $end
$upscope $end
$upscope $end
$upscope $end
$enddefinitions $end
#0
$dumpvars
bx 1
bx 0
bx /
x.
bx -
b1010011 ,
x+
b10011010 *
x)
0(
x'
b1010011 &
0%
1$
bx #
0"
x!
$end
#10000
bz #
bz -
b0 1
0.
b0 0
0)
0$
1"
b110100 *
1'
1+
1(
1%
#20000
0%
#30000
b1 0
b0xxxxxxx /
b1 1
0!
0"
b1101000 *
1%
#40000
0%
#50000
b0xxxxxx /
1!
1)
b10 1
b10 0
1"
b11010000 *
1%
#60000
0%
#70000
b1xxxxx /
0!
b11 1
b11 0
0"
b10100000 *
1%
#80000
0%
#90000
b11xxxx /
1!
0)
b100 1
b100 0
1"
b1000000 *
1%
#100000
0%
#110000
b110xxx /
0!
1)
b101 1
b101 0
0"
b10000000 *
1%
#120000
0%
#130000
b1101xx /
0)
b110 1
b110 0
1"
b0 *
1%
#140000
0%
#150000
b11010x /
1!
b111 1
b111 0
0"
1%
#160000
0%
#170000
b110100 /
b1000 1
b1000 0
1"
1%
#180000
0%
#190000
bz /
z!
b0 1
b0 0
0"
1%
#200000
0%
#210000
b1 0
b0zzzzzzz /
b1 1
0!
1"
1%
#220000
0%
#230000
b0zzzzzz /
1!
b10 1
b10 0
0"
1%
#240000
0%
#250000
b0zzzzz /
0!
b11 1
b11 0
1"
1%
#260000
0%
#270000
b0zzzz /
1!
b100 1
b100 0
0"
1%
#280000
0%
#290000
b0zzz /
0!
b101 1
b101 0
1"
1%
#300000
0%
#310000
b0zz /
b110 1
b110 0
0"
1%
#320000
0%
#330000
b0z /
1!
b111 1
b111 0
1"
1%
#340000
0%
#350000
b0 /
b1000 1
b1000 0
0"
1%
#360000
0%
#370000
bz /
z!
b0 1
b0 0
1"
1%
#380000
0%
#390000
b1 0
b0zzzzzzz /
b1 1
0!
0"
1%
#400000
0%
#410000
1!
b10 1
1"
1%
0'
#420000
0%
#430000
0!
b11 1
0"
1%
#440000
0%
#450000
1!
b100 1
1"
1%
#460000
0%
#470000
0!
b101 1
0"
1%
#480000
0%
#490000
b110 1
1"
1%
#500000
0%
#510000
1!
b111 1
0"
1%
#520000
0%
#530000
b1000 1
1"
1%
#540000
0%
#550000
z!
b0 1
0"
1%
#560000
0%
#570000
b1 1
0!
1"
1%
#580000
0%
#590000
1!
b10 1
0"
1%
#600000
0%
#610000
0!
b11 1
1"
1%
#620000
0%
#630000
1!
b100 1
0"
1%
#640000
0%
#650000
0!
b101 1
1"
1%
#660000
0%
#670000
b110 1
0"
1%
#680000
0%
#690000
1!
b111 1
1"
1%
#700000
0%
#710000
b1000 1
0"
1%
#720000
0%
#730000
z!
b0 1
1"
1%
#740000
0%
#750000
b1 1
0!
0"
1%
#760000
0%
#770000
1!
b10 1
1"
1%
#780000
0%
#790000
0!
b11 1
0"
1%
#800000
0%
#810000
1!
b100 1
1"
1%
#820000
0%
#830000
0!
b101 1
0"
1%
#840000
0%
#850000
b110 1
1"
1%
#860000
0%
#870000
1!
b111 1
0"
1%
#880000
0%
#890000
b1000 1
1"
1%
#900000
0%
#910000
z!
b0 1
0"
1%
#920000
0%
#930000
b1 1
0!
1"
1%
#940000
0%
#950000
1!
b10 1
0"
1%
#960000
0%
#970000
0!
b11 1
1"
1%
#980000
0%
#990000
1!
b100 1
0"
1%
#1000000
0%
#1010000
0!
b101 1
1"
1%
